questionify/__init__.py
questionify/questionify.py
questionify-0.0.2.dist-info/LICENSE.txt
questionify-0.0.2.dist-info/METADATA
questionify-0.0.2.dist-info/WHEEL
questionify-0.0.2.dist-info/top_level.txt
questionify-0.0.2.dist-info/RECORD
