Metadata-Version: 2.1
Name: questionify
Version: 0.0.2
Summary: Desktop-based software to help you study
Home-page: https://www.intjelic.me/project/questionify
Author: Jonathan De Wachter
Author-email: dewachter.jonathan@gmail.com
License: UNKNOWN
Project-URL: Website, https://www.intjelic.me/project/questionify
Project-URL: Repository, https://github.com/intjelic/questionify
Platform: UNKNOWN
Classifier: Development Status :: 1 - Planning
Classifier: Environment :: MacOS X
Classifier: Environment :: Win32 (MS Windows)
Classifier: Environment :: X11 Applications :: Qt
Classifier: Intended Audience :: End Users/Desktop
Classifier: License :: OSI Approved :: GNU General Public License v3 or later (GPLv3+)
Classifier: Natural Language :: English
Classifier: Operating System :: OS Independent
Classifier: Programming Language :: Python :: 3
Classifier: Topic :: Education
Requires-Python: >=3.6
